relnotegen/__init__.py
relnotegen/relnotegen.py
relnotegen-0.1.3.dist-info/LICENSE
relnotegen-0.1.3.dist-info/METADATA
relnotegen-0.1.3.dist-info/WHEEL
relnotegen-0.1.3.dist-info/entry_points.txt
relnotegen-0.1.3.dist-info/top_level.txt
relnotegen-0.1.3.dist-info/RECORD
