Metadata-Version: 2.1
Name: relnotegen
Version: 0.1.3
Summary: A tool to generate release notes from a set of markdown files
Home-page: https://github.com/nielsvanspauwen/relnotegen
Author: Niels Vanspauwen
Author-email: niels.vanspauwen@gmail.com
License: MIT
Project-URL: Source, https://github.com/nielsvanspauwen/relnotegen
Project-URL: Tracker, https://github.com/nielsvanspauwen/relnotegen/issues
Keywords: release notes markdown
Classifier: Development Status :: 3 - Alpha
Classifier: Intended Audience :: Developers
Classifier: License :: OSI Approved :: MIT License
Classifier: Programming Language :: Python :: 3.6
Classifier: Programming Language :: Python :: 3.7
Classifier: Programming Language :: Python :: 3.8
Classifier: Programming Language :: Python :: 3.9
Requires-Python: >=3.6
License-File: LICENSE
Requires-Dist: Jinja2 ==3.1.2
Requires-Dist: Markdown ==3.5.1
Requires-Dist: packaging ==23.2
